{"app":"Flashpost","id":"282330da-7d0e-4b3e-99fa-6c6c726446ad","name":"Events","version":"1.0","type":"collections","createdTime":"05-Dec-2025 13:15:01","exportedDate":"05-Dec-2025 13:16:11","collections":[{"id":"282330da-7d0e-4b3e-99fa-6c6c726446ad","parent":"0","text":"Events","createdTime":"05-Dec-2025 13:15:01","droppable":true,"data":{"treeNodeType":"collection","variableId":""},"relativeIndex":0},{"id":"3077549d-ba84-4a3a-ba97-d7a6cfbdfbad","parent":"282330da-7d0e-4b3e-99fa-6c6c726446ad","text":"127.0.0.1:3000/api/events","createdTime":"05-Dec-2025 14:14:25","droppable":false,"data":{"id":"cf6d01b4-427e-4f8b-a821-8dc4162ee887","method":"get","name":"127.0.0.1:3000/api/events","url":"127.0.0.1:3000/api/events","createdTime":"05-Dec-2025 14:14:25","$loki":15,"treeNodeType":"request"}}],"requests":[{"id":"3077549d-ba84-4a3a-ba97-d7a6cfbdfbad","url":"127.0.0.1:3000/api/events","name":"127.0.0.1:3000/api/events","createdTime":"05-Dec-2025 14:14:25","method":"get","params":[{"isChecked":false,"key":"","value":""}],"pathParams":[],"auth":{"authType":"noauth","userName":"","password":"","addTo":"queryparams","showPwd":false,"tokenPrefix":"","aws":{"service":"","region":"","accessKey":"","secretAccessKey":"","sessionToken":""}},"headers":[{"key":"Accept","value":"*/*","isChecked":true},{"key":"User-Agent","value":"Flashpost","isChecked":true},{"key":"","value":"","isChecked":false}],"body":{"bodyType":"none","formdata":[{"isChecked":false,"key":"","value":""}],"urlencoded":[{"isChecked":false,"key":"","value":""}],"raw":{"data":"","lang":"json"},"binary":{"fileName":"","data":{},"contentTypeOption":"manual"},"graphql":{"query":"","variables":""}},"tests":[{"parameter":"","action":"","expectedValue":""}],"setvar":[{"parameter":"","key":"","variableName":""}],"notes":"","selectedEnvironmentId":"3958dd3c-7ab2-4660-b2da-3210a392fc17"}]}